<Namespace Name="System.Data.Common.CommandTrees">
  <Docs>
    <summary>The <see cref="N:System.Data.Common.CommandTrees" /> namespace provides classes to build expressions that make up a command tree.</summary>
    <remarks>
      <format type="text/markdown"><![CDATA[  
  
## Remarks  
 A command trees is an object model representation of a query that can be used to represent query, update, insert, and delete commands in the ADO.NET Entity Data Model (EDM) and storage metadata.  
  
 ]]></format>
    </remarks>
  </Docs>
</Namespace>